miio/__init__.py
miio/airconditioner_miot.py
miio/airconditioningcompanion.py
miio/airconditioningcompanionMCN.py
miio/airdehumidifier.py
miio/airfilter_util.py
miio/airfresh.py
miio/airfresh_t2017.py
miio/airhumidifier.py
miio/airhumidifier_jsq.py
miio/airhumidifier_miot.py
miio/airhumidifier_mjjsq.py
miio/airpurifier.py
miio/airpurifier_airdog.py
miio/airpurifier_miot.py
miio/airqualitymonitor.py
miio/airqualitymonitor_miot.py
miio/alarmclock.py
miio/aqaracamera.py
miio/chuangmi_camera.py
miio/chuangmi_ir.py
miio/chuangmi_plug.py
miio/cli.py
miio/click_common.py
miio/cooker.py
miio/curtain_youpin.py
miio/data/cooker_profiles.json
miio/device.py
miio/deviceinfo.py
miio/discovery.py
miio/exceptions.py
miio/extract_tokens.py
miio/fan_common.py
miio/gateway/__init__.py
miio/gateway/alarm.py
miio/gateway/devices/__init__.py
miio/gateway/devices/light.py
miio/gateway/devices/sensor.py
miio/gateway/devices/subdevice.py
miio/gateway/devices/subdevices.yaml
miio/gateway/devices/switch.py
miio/gateway/gateway.py
miio/gateway/gatewaydevice.py
miio/gateway/light.py
miio/gateway/radio.py
miio/gateway/zigbee.py
miio/heater.py
miio/heater_miot.py
miio/huizuo.py
miio/integrations/__init__.py
miio/integrations/fan/__init__.py
miio/integrations/fan/dmaker/__init__.py
miio/integrations/fan/dmaker/fan.py
miio/integrations/fan/dmaker/fan_miot.py
miio/integrations/fan/dmaker/test_fan.py
miio/integrations/fan/dmaker/test_fan_miot.py
miio/integrations/fan/leshow/__init__.py
miio/integrations/fan/leshow/fan_leshow.py
miio/integrations/fan/leshow/tests/__init__.py
miio/integrations/fan/leshow/tests/test_fan_leshow.py
miio/integrations/fan/zhimi/__init__.py
miio/integrations/fan/zhimi/fan.py
miio/integrations/fan/zhimi/test_fan.py
miio/integrations/fan/zhimi/test_zhimi_miot.py
miio/integrations/fan/zhimi/zhimi_miot.py
miio/integrations/humidifier/__init__.py
miio/integrations/humidifier/deerma/__init__.py
miio/integrations/humidifier/deerma/airhumidifier_jsqs.py
python_miio-0.5.11.dist-info/entry_points.txt
python_miio-0.5.11.dist-info/LICENSE
python_miio-0.5.11.dist-info/LICENSE.md
python_miio-0.5.11.dist-info/WHEEL
python_miio-0.5.11.dist-info/METADATA
python_miio-0.5.11.dist-info/RECORD
