Metadata-Version: 2.1
Name: python-miio
Version: 0.5.11
Summary: Python library for interfacing with Xiaomi smart appliances
Home-page: https://github.com/rytilahti/python-miio
License: GPL-3.0-only
Keywords: xiaomi,miio,miot,smart home
Author: Teemu R
Author-email: tpr@iki.fi
Requires-Python: >=3.7,<4.0
Classifier: License :: OSI Approved :: GNU General Public License v3 (GPLv3)
Classifier: Programming Language :: Python :: 3
Classifier: Programming Language :: Python :: 3.10
Classifier: Programming Language :: Python :: 3.7
Classifier: Programming Language :: Python :: 3.8
Classifier: Programming Language :: Python :: 3.9
Provides-Extra: docs
Requires-Dist: PyYAML (>=5,<7)
Requires-Dist: android_backup (>=0,<1)
Requires-Dist: appdirs (>=1,<2)
Requires-Dist: attrs
Requires-Dist: click (>=7)
Requires-Dist: construct (>=2.10.56,<3.0.0)
Requires-Dist: croniter (>=1)
Requires-Dist: cryptography (>=35)
Requires-Dist: defusedxml (>=0,<1)
Requires-Dist: importlib_metadata (>=1,<2); python_version <= "3.7"
Requires-Dist: netifaces (>=0,<1)
Requires-Dist: pytz
Requires-Dist: sphinx (>=4.2); extra == "docs"
Requires-Dist: sphinx_click; extra == "docs"
Requires-Dist: sphinx_rtd_theme (>=0,<1); extra == "docs"
Requires-Dist: sphinxcontrib-apidoc (>=0,<1); extra == "docs"
Requires-Dist: tqdm (>=4,<5)
Requires-Dist: zeroconf (>=0,<1)
Project-URL: Documentation, https://python-miio.readthedocs.io
Project-URL: Repository, https://github.com/rytilahti/python-miio
